cogsol/__init__.py
cogsol/definitions.py
cogsol-0.1.1.dist-info/LICENSE
cogsol-0.1.1.dist-info/METADATA
cogsol-0.1.1.dist-info/WHEEL
cogsol-0.1.1.dist-info/top_level.txt
cogsol-0.1.1.dist-info/RECORD
